LICENSE.txt
MANIFEST.in
README.rst
setup.py
django_organisms.egg-info/PKG-INFO
django_organisms.egg-info/SOURCES.txt
django_organisms.egg-info/dependency_links.txt
django_organisms.egg-info/requires.txt
django_organisms.egg-info/top_level.txt
organisms/__init__.py
organisms/api.py
organisms/models.py
organisms/tests.py
organisms/management/__init__.py
organisms/management/commands/__init__.py
organisms/management/commands/organisms_create_or_update.py
organisms/migrations/0001_initial.py
organisms/migrations/__init__.py