Metadata-Version: 1.1
Name: django-organisms
Version: 0.4
Summary: A simple Django app to represent organisms.
Home-page: https://bitbucket.org/greenelab/django-organisms
Author: Greene Lab
Author-email: team@greenelab.com
License: LICENSE.txt
Platform: UNKNOWN
Classifier: Environment :: Web Environment
Classifier: Framework :: Django
Classifier: Intended Audience :: Developers
Classifier: License :: OSI Approved :: BSD License
Classifier: Operating System :: OS Independent
Classifier: Programming Language :: Python
Classifier: Programming Language :: Python :: 2.7
Classifier: Topic :: Scientific/Engineering :: Bio-Informatics
